LICENSE
README.md
setup.py
jlogger/__init__.py
jlogger/j_heartbeat.py
jlogger/j_logger.py
jlogger.egg-info/PKG-INFO
jlogger.egg-info/SOURCES.txt
jlogger.egg-info/dependency_links.txt
jlogger.egg-info/top_level.txt
test/test.py